nb_cli_plugin_webui/__init__.py
nb_cli_plugin_webui/app/__init__.py
nb_cli_plugin_webui/app/application.py
nb_cli_plugin_webui/app/auth/__init__.py
nb_cli_plugin_webui/app/auth/constants.py
nb_cli_plugin_webui/app/auth/exceptions.py
nb_cli_plugin_webui/app/auth/router.py
nb_cli_plugin_webui/app/auth/schemas.py
nb_cli_plugin_webui/app/auth/utils.py
nb_cli_plugin_webui/app/config.py
nb_cli_plugin_webui/app/constants.py
nb_cli_plugin_webui/app/exceptions.py
nb_cli_plugin_webui/app/file/__init__.py
nb_cli_plugin_webui/app/file/constants.py
nb_cli_plugin_webui/app/file/exceptions.py
nb_cli_plugin_webui/app/file/router.py
nb_cli_plugin_webui/app/file/schemas.py
nb_cli_plugin_webui/app/file/utils.py
nb_cli_plugin_webui/app/handlers/__init__.py
nb_cli_plugin_webui/app/handlers/nonebot.py
nb_cli_plugin_webui/app/handlers/pip.py
nb_cli_plugin_webui/app/handlers/plugin.py
nb_cli_plugin_webui/app/handlers/process/__init__.py
nb_cli_plugin_webui/app/handlers/process/constants.py
nb_cli_plugin_webui/app/handlers/process/exceptions.py
nb_cli_plugin_webui/app/handlers/process/impl.py
nb_cli_plugin_webui/app/handlers/process/log.py
nb_cli_plugin_webui/app/handlers/process/process.py
nb_cli_plugin_webui/app/handlers/process/schemas.py
nb_cli_plugin_webui/app/handlers/process/utils.py
nb_cli_plugin_webui/app/handlers/project.py
nb_cli_plugin_webui/app/handlers/store.py
nb_cli_plugin_webui/app/logging.py
nb_cli_plugin_webui/app/middlewares.py
nb_cli_plugin_webui/app/process/__init__.py
nb_cli_plugin_webui/app/process/constants.py
nb_cli_plugin_webui/app/process/dependencies.py
nb_cli_plugin_webui/app/process/exceptions.py
nb_cli_plugin_webui/app/process/router.py
nb_cli_plugin_webui/app/process/service.py
nb_cli_plugin_webui/app/project/__init__.py
nb_cli_plugin_webui/app/project/config/__init__.py
nb_cli_plugin_webui/app/project/config/constants.py
nb_cli_plugin_webui/app/project/config/exceptions.py
nb_cli_plugin_webui/app/project/config/router.py
nb_cli_plugin_webui-0.4.2.dist-info/LICENSE
nb_cli_plugin_webui-0.4.2.dist-info/METADATA
nb_cli_plugin_webui-0.4.2.dist-info/WHEEL
nb_cli_plugin_webui-0.4.2.dist-info/entry_points.txt
nb_cli_plugin_webui-0.4.2.dist-info/RECORD
