Metadata-Version: 2.1
Name: nb-cli-plugin-webui
Version: 0.4.2
Summary: web ui support for nb-cli
Home-page: https://github.com/nonebot/cli-plugin-webui
License: MIT
Keywords: nonebot,cli,web
Author: Kyomotoi
Author-email: kyomotoiowo@gmail.com
Requires-Python: >=3.8.1,<4.0.0
Classifier: Development Status :: 5 - Production/Stable
Classifier: Framework :: Robot Framework
Classifier: Framework :: Robot Framework :: Library
Classifier: License :: OSI Approved :: MIT License
Classifier: Operating System :: OS Independent
Classifier: Programming Language :: Python :: 3
Classifier: Programming Language :: Python :: 3.9
Classifier: Programming Language :: Python :: 3.10
Classifier: Programming Language :: Python :: 3.11
Classifier: Programming Language :: Python :: 3.12
Requires-Dist: APScheduler (>=3.10.1,<4.0.0)
Requires-Dist: PyJWT (>=2.7.0,<3.0.0)
Requires-Dist: WMI (>=1.5.1,<2.0.0) ; sys_platform == "win32"
Requires-Dist: bcrypt (>=4.0.1,<5.0.0)
Requires-Dist: fastapi (>=0.95.1,<0.96.0)
Requires-Dist: httpx[socks] (>=0.24.1,<0.25.0)
Requires-Dist: loguru (>=0.7.0,<0.8.0)
Requires-Dist: nb-cli (>=1.2.3,<2.0.0)
Requires-Dist: passlib (>=1.7.4,<2.0.0)
Requires-Dist: pathlib (>=1.0.1,<2.0.0)
Requires-Dist: psutil (>=5.9.5,<6.0.0)
Requires-Dist: python-dotenv (>=1.0.0,<2.0.0)
Requires-Dist: uvicorn[standard] (>=0.22.0,<0.23.0)
Project-URL: Documentation, https://github.com/nonebot/cli-plugin-webui
Project-URL: Repository, https://github.com/nonebot/cli-plugin-webui
